acrux/__init__.py
acrux/categorical.py
acrux/eda.py
acrux/generator.py
acrux/heatmap.py
acrux/numeric.py
acrux/pair_numeric.py
acrux/utils.py
acrux-2.0.dist-info/LICENSE
acrux-2.0.dist-info/METADATA
acrux-2.0.dist-info/WHEEL
acrux-2.0.dist-info/top_level.txt
acrux-2.0.dist-info/RECORD
