Metadata-Version: 2.1
Name: acrux
Version: 2.0
Summary: Simple Exploratory Data Analysis tool.
Home-page: https://github.com/darkhan-ai/acrux
License: MIT
License-File: LICENSE
Requires-Dist: pandas
Requires-Dist: matplotlib
Requires-Dist: seaborn
Requires-Dist: joblib
Requires-Dist: tqdm
